{
  "db_name": "SQLite",
  "query": "\n        INSERT INTO playback_history (profile_id, content_id, content_type, position_ms, duration_ms, progress_pct, watched, updated_at)\n        VALUES (?, ?, ?, ?, ?, ?, ?, ?)\n        ON CONFLICT(profile_id, content_id) DO UPDATE SET\n            position_ms = excluded.position_ms,\n            duration_ms = excluded.duration_ms,\n            progress_pct = excluded.progress_pct,\n            watched = excluded.watched,\n            updated_at = excluded.updated_at\n        ",
  "describe": {
    "columns": [],
    "parameters": {
      "Right": 8
    },
    "nullable": []
  },
  "hash": "0314095698983c0b9c8cb8bc3d56e5ac19ca83aab8946c626e790807f6f9dcf6"
}
